robotframework_debug_adapter/__init__.py
robotframework_debug_adapter/__main__.py
robotframework_debug_adapter/_ignore_failures_in_stack.py
robotframework_debug_adapter/base_launch_process_target.py
robotframework_debug_adapter/constants.py
robotframework_debug_adapter/debug_adapter_comm.py
robotframework_debug_adapter/debugger_impl.py
robotframework_debug_adapter/events_listener.py
robotframework_debug_adapter/file_utils.py
robotframework_debug_adapter/global_vars.py
robotframework_debug_adapter/launch_process.py
robotframework_debug_adapter/launch_process_pydevd_comm.py
robotframework_debug_adapter/launch_process_robot_target_comm.py
robotframework_debug_adapter/listeners.py
robotframework_debug_adapter/message_utils.py
robotframework_debug_adapter/prerun_modifiers.py
robotframework_debug_adapter/protocols.py
robotframework_debug_adapter/run_robot__main__.py
robotframework_debug_adapter/safe_repr.py
robotframework_debug_adapter/vendored/README.md
robotframework_debug_adapter/vendored/__init__.py
robotframework_debug_adapter/vendored/force_pydevd.py
robotframework_debug_adapter/vendored/vendored_pydevd/LICENSE
robotframework_debug_adapter/vendored/vendored_pydevd/conftest.py
robotframework_debug_adapter/vendored/vendored_pydevd/gradlew.bat
robotframework_debug_adapter/vendored/vendored_pydevd/interpreterInfo.py
robotframework_debug_adapter/vendored/vendored_pydevd/pycompletionserver.py
robotframework_debug_adapter/vendored/vendored_pydevd/pydev_app_engine_debug_startup.py
robotframework_debug_adapter/vendored/vendored_pydevd/pydev_coverage.py
robotframework_debug_adapter/vendored/vendored_pydevd/pydev_pysrc.py
robotframework_debug_adapter/vendored/vendored_pydevd/pydev_run_in_console.py
robotframework_debug_adapter/vendored/vendored_pydevd/pydevconsole.py
robotframework_debug_adapter/vendored/vendored_pydevd/pydevd.py
robotframework_debug_adapter/vendored/vendored_pydevd/pydevd_file_utils.py
robotframework_debug_adapter/vendored/vendored_pydevd/pydevd_tracing.py
robotframework_ls/vendored/robocorp_ls_core/libs/fsnotify_lib/fsnotify-0.2.1.dist-info/LICENSE
robotframework_ls/vendored/robocorp_ls_core/libs/robocop_lib/pathspec-0.11.1.dist-info/LICENSE
robotframework_ls/vendored/robocorp_ls_core/libs/robocop_lib/python_dateutil-2.8.2.dist-info/LICENSE
robotframework_ls/vendored/robocorp_ls_core/libs/robocop_lib/robotframework_robocop-3.1.1.dist-info/LICENSE
robotframework_ls/vendored/robocorp_ls_core/libs/robocop_lib/six-1.16.0.dist-info/LICENSE
robotframework_ls/vendored/robocorp_ls_core/libs/robocop_lib/tomli-2.0.1.dist-info/LICENSE
robotframework_ls/vendored/robocorp_ls_core/libs/robotidy_lib/pathspec-0.11.2.dist-info/LICENSE
robotframework_ls/vendored/robocorp_ls_core/libs/robotidy_lib/robotframework_tidy-4.5.0.dist-info/LICENSE
robotframework_ls/vendored/robocorp_ls_core/libs/robotidy_lib/tomli-2.0.1.dist-info/LICENSE
robotframework_ls/vendored/robocorp_ls_core/libs/watchdog_lib/watchdog-2.1.9.dist-info/LICENSE
robotframework_ls/vendored/robocorp_ls_core/libs/yaml_lib/PyYAML-6.0.dist-info/LICENSE
robotframework_lsp-1.13.0.dist-info/LICENSE
robotframework_lsp-1.13.0.dist-info/METADATA
robotframework_lsp-1.13.0.dist-info/WHEEL
robotframework_lsp-1.13.0.dist-info/entry_points.txt
robotframework_lsp-1.13.0.dist-info/top_level.txt
robotframework_lsp-1.13.0.dist-info/RECORD
