Metadata-Version: 2.1
Name: robotframework-lsp
Version: 1.13.0
Summary: Language Server Protocol implementation for Robot Framework
Home-page: https://github.com/robocorp/robotframework-lsp
Author: Fabio Zadrozny
License: Apache-2.0
Classifier: Development Status :: 5 - Production/Stable
Classifier: Environment :: Console
Classifier: Intended Audience :: Developers
Classifier: License :: OSI Approved :: Apache Software License
Classifier: Operating System :: MacOS :: MacOS X
Classifier: Operating System :: Microsoft :: Windows
Classifier: Operating System :: POSIX
Classifier: Programming Language :: Python
Classifier: Programming Language :: Python :: 3.7
Classifier: Programming Language :: Python :: 3.8
Classifier: Programming Language :: Python :: 3.9
Classifier: Programming Language :: Python :: 3.10
Classifier: Programming Language :: Python :: 3.11
Classifier: Topic :: Text Editors
Classifier: Topic :: Text Editors :: Integrated Development Environments (IDE)
Classifier: Topic :: Software Development :: Debuggers
Classifier: Framework :: Robot Framework
Classifier: Framework :: Robot Framework :: Tool
Requires-Python: >=3.7
License-File: LICENSE
Requires-Dist: robotframework>=3.2
Provides-Extra: selenium
Requires-Dist: robotframework-seleniumlibrary>=4.4; extra == "selenium"
Provides-Extra: test
Requires-Dist: mock; extra == "test"
Requires-Dist: pytest; extra == "test"
Requires-Dist: pytest-regressions==1.0.6; extra == "test"
Requires-Dist: pytest-xdist; extra == "test"
Requires-Dist: pytest-timeout; extra == "test"
